CREATURE_WORLD_BUILDER_LITE/creature_world_builder_lite.py
CREATURE_WORLD_BUILDER_LITE/creature_world_builder_lite_tests.py
CREATURE_WORLD_BUILDER_LITE-1.dist-info/LICENSE
CREATURE_WORLD_BUILDER_LITE-1.dist-info/METADATA
CREATURE_WORLD_BUILDER_LITE-1.dist-info/WHEEL
CREATURE_WORLD_BUILDER_LITE-1.dist-info/entry_points.txt
CREATURE_WORLD_BUILDER_LITE-1.dist-info/top_level.txt
CREATURE_WORLD_BUILDER_LITE-1.dist-info/RECORD
