Metadata-Version: 2.1
Name: CREATURE-WORLD-BUILDER-LITE
Version: 1
Summary: This package contains implementation of the offline strategy RPG "Creature World Builder Lite" on command line interface.
Home-page: https://github.com/DigitalCreativeApkDev/CREATURE_WORLD_BUILDER_LITE
Author: DigitalCreativeApkDev
Author-email: digitalcreativeapkdev2022@gmail.com
License: MIT
Platform: UNKNOWN
Classifier: Programming Language :: Python :: 3
Classifier: Programming Language :: Python :: 3.7
